{
    "Commit Sha": "4226546b4636801b220c75a19d029972293a0c70",
    "CN": {
        "activity": {
            "name": "促融共竞#1",
            "time": 1742457600
        },
        "last_updated": "2025-03-25 07:44:02.336"
    },
    "TW": {
        "activity": {
            "name": "孤星·復刻",
            "time": 1742457600
        },
        "last_updated": "2025-03-20 08:08:02.960"
    },
    "EN": {
        "activity": {
            "name": "Delicious On Terra",
            "time": 1741626000
        },
        "last_updated": "2025-03-10 17:28:24.806"
    },
    "JP": {
        "activity": {
            "name": "鋒矢突破",
            "time": 1742886000
        },
        "last_updated": "2025-03-25 07:44:02.657"
    },
    "KR": {
        "activity": {
            "name": "벡터 돌파",
            "time": 1742886000
        },
        "last_updated": "2025-03-25 07:44:02.659"
    }
}